MANIFEST.in
README
generate.py
setup.py
chealpy/__init__.py
chealpy/chealpix.c
chealpy/chealpix.h
chealpy/compress.c
chealpy/compress.pyx
chealpy/high.c
chealpy/high.pyx
chealpy/hp_compress.c
chealpy/hp_compress.h
chealpy/low.c
chealpy/low.pyx
chealpy/test_chealpy.py
chealpy/test_compress.py
chealpy/version.py
chealpy.egg-info/PKG-INFO
chealpy.egg-info/SOURCES.txt
chealpy.egg-info/dependency_links.txt
chealpy.egg-info/not-zip-safe
chealpy.egg-info/requires.txt
chealpy.egg-info/top_level.txt