Metadata-Version: 1.0
Name: chealpy
Version: 0.1.3
Summary: Python Binding of chealpix
Home-page: http://github.com/rainwoodman/chealpy
Author: Yu Feng
Author-email: yfeng1@berkeley.edu
License: GPLv2+
Platform: UNKNOWN
